{
  "updatedAt": "2026-07-03T01:03:08.033Z",
  "bindingVersion": 8,
  "embedBinding": {
    "bein-max-1": "vip1",
    "bein-max-2": "vip2",
    "bein-max-3": "vip1",
    "bein-max-4": "vip2",
    "bein-sports-1": "vip2",
    "bein-sports-2": "vip1"
  },
  "liveCount": 1,
  "routes": [
    {
      "id": "espn-fifa.world-760496",
      "home": "Portugal",
      "away": "Croatia",
      "score": "2 - 1",
      "minute": "90'+13'",
      "channelId": "bein-sports-1",
      "channel": null,
      "commentator": null,
      "embedKey": "vip2",
      "embedUrl": "https://vip.worldkoora.com/albaplayer/vip2/",
      "kickoffUtc": "2026-07-02T23:00Z"
    }
  ],
  "conflicts": [],
  "ok": true,
  "warning": null
}