{
  "mexico~southafrica": [
    {
      "type": "tweet",
      "url": "https://x.com/TrollFootball/status/2065178045246484698",
      "text": "Referee of Mexico vs South Africa https://t.co/qUq3Ofz8ZQ",
      "author": "TrollFootball",
      "tweetId": "2065178045246484698",
      "likes": 70201,
      "retweets": 5609,
      "engagement": 82288,
      "postedAt": "2026-06-11T21:03:09.000Z",
      "avatarUrl": "https://pbs.twimg.com/profile_images/2007448817789194242/VzLmM12q_normal.jpg",
      "media": [
        {
          "type": "photo",
          "previewUrl": "https://pbs.twimg.com/media/HKj8dEdagAARbv5.jpg",
          "url": "https://pbs.twimg.com/media/HKj8dEdagAARbv5.jpg"
        }
      ]
    },
    {
      "type": "tweet",
      "url": "https://x.com/TrollFootball/status/2065182112790274207",
      "text": "Mexico vs South Africa referee highlights https://t.co/xyyiImzv6L",
      "author": "TrollFootball",
      "tweetId": "2065182112790274207",
      "likes": 9999,
      "retweets": 976,
      "engagement": 12094,
      "postedAt": "2026-06-11T21:19:19.000Z",
      "avatarUrl": "https://pbs.twimg.com/profile_images/2007448817789194242/VzLmM12q_normal.jpg",
      "media": [
        {
          "type": "video",
          "previewUrl": "https://pbs.twimg.com/amplify_video_thumb/2065181156216299520/img/zAS2hVJj6VUWn1bZ.jpg",
          "url": "https://video.twimg.com/amplify_video/2065181156216299520/vid/avc1/480x726/OOOUgEiCGXTJT5O0.mp4"
        }
      ]
    },
    {
      "type": "tweet",
      "url": "https://x.com/memesvsfootball/status/2065182283242295794",
      "text": "Mexico vs. South Africa https://t.co/T61GjQU5ud",
      "author": "memesvsfootball",
      "tweetId": "2065182283242295794",
      "likes": 18723,
      "retweets": 303,
      "engagement": 19340,
      "postedAt": "2026-06-11T21:20:00.000Z",
      "avatarUrl": "https://pbs.twimg.com/profile_images/2017804319270309895/TqBzYvKY_normal.png",
      "media": [
        {
          "type": "photo",
          "previewUrl": "https://pbs.twimg.com/media/HKj__-lawAA_ahy.jpg",
          "url": "https://pbs.twimg.com/media/HKj__-lawAA_ahy.jpg"
        }
      ]
    }
  ],
  "czechia~southkorea": [
    {
      "type": "tweet",
      "url": "https://x.com/TrollFootball/status/2065293753196450250",
      "text": "South Korea vs Czechia highlights https://t.co/fxwg2vB9U9",
      "author": "TrollFootball",
      "tweetId": "2065293753196450250",
      "likes": 18482,
      "retweets": 784,
      "engagement": 20196,
      "postedAt": "2026-06-12T04:42:56.000Z",
      "avatarUrl": "https://pbs.twimg.com/profile_images/2007448817789194242/VzLmM12q_normal.jpg",
      "media": [
        {
          "type": "video",
          "previewUrl": "https://pbs.twimg.com/amplify_video_thumb/2065292580796215296/img/3rYtjK0sSuCASUWq.jpg",
          "url": "https://video.twimg.com/amplify_video/2065292580796215296/vid/avc1/720x924/v01IfM_J221zIHtj.mp4"
        }
      ]
    }
  ],
  "bosniaherzegovina~canada": [
    {
      "type": "tweet",
      "url": "https://x.com/TrollFootball/status/2065544550366773394",
      "text": "Canada earn their first ever World Cup point… https://t.co/1V1nBubYkw",
      "author": "TrollFootball",
      "tweetId": "2065544550366773394",
      "likes": 23396,
      "retweets": 751,
      "engagement": 24971,
      "postedAt": "2026-06-12T21:19:31.000Z",
      "avatarUrl": "https://pbs.twimg.com/profile_images/2007448817789194242/VzLmM12q_normal.jpg",
      "media": [
        {
          "type": "photo",
          "previewUrl": "https://pbs.twimg.com/media/HKpJsVjbIAAA-Hk.jpg",
          "url": "https://pbs.twimg.com/media/HKpJsVjbIAAA-Hk.jpg"
        }
      ]
    },
    {
      "type": "tweet",
      "url": "https://x.com/TrollFootball/status/2065540644224069666",
      "text": "Jesse Marsch (Canada coach): 'We couldn't win because we were playing against 2 countries… Bosnia and Herzegovina.' https://t.co/pm4xbHwbYF",
      "author": "TrollFootball",
      "tweetId": "2065540644224069666",
      "likes": 13222,
      "retweets": 698,
      "engagement": 14808,
      "postedAt": "2026-06-12T21:04:00.000Z",
      "avatarUrl": "https://pbs.twimg.com/profile_images/2007448817789194242/VzLmM12q_normal.jpg",
      "media": [
        {
          "type": "photo",
          "previewUrl": "https://pbs.twimg.com/media/HKpB3RHaAAAF8oa.jpg",
          "url": "https://pbs.twimg.com/media/HKpB3RHaAAAF8oa.jpg"
        }
      ]
    }
  ],
  "paraguay~unitedstates": [
    {
      "type": "tweet",
      "url": "https://x.com/TrollFootball/status/2065631106330927565",
      "text": "USA vs Paraguay https://t.co/v4SJ0hjhD3",
      "author": "TrollFootball",
      "tweetId": "2065631106330927565",
      "likes": 18942,
      "retweets": 1473,
      "engagement": 22048,
      "postedAt": "2026-06-13T03:03:27.000Z",
      "avatarUrl": "https://pbs.twimg.com/profile_images/2007448817789194242/VzLmM12q_normal.jpg",
      "media": [
        {
          "type": "photo",
          "previewUrl": "https://pbs.twimg.com/media/HKqYfo5aEAA0TZp.jpg",
          "url": "https://pbs.twimg.com/media/HKqYfo5aEAA0TZp.jpg"
        }
      ]
    },
    {
      "type": "tweet",
      "url": "https://x.com/TrollFootball/status/2065632835881623852",
      "text": "USA team against Paraguay\n\n https://t.co/vkRYepjt9y",
      "author": "TrollFootball",
      "tweetId": "2065632835881623852",
      "likes": 19264,
      "retweets": 991,
      "engagement": 21405,
      "postedAt": "2026-06-13T03:10:20.000Z",
      "avatarUrl": "https://pbs.twimg.com/profile_images/2007448817789194242/VzLmM12q_normal.jpg",
      "media": [
        {
          "type": "video",
          "previewUrl": "https://pbs.twimg.com/amplify_video_thumb/2065632223282573312/img/b-jW7YCw9pnMa6wy.jpg",
          "url": "https://video.twimg.com/amplify_video/2065632223282573312/vid/avc1/1280x720/o-EJquyuZLAvguoy.mp4"
        }
      ]
    },
    {
      "type": "tweet",
      "url": "https://x.com/memesvsfootball/status/2065630910125686799",
      "text": "USA vs. Paraguay https://t.co/voPIBXNIp8",
      "author": "memesvsfootball",
      "tweetId": "2065630910125686799",
      "likes": 72,
      "retweets": 4,
      "engagement": 82,
      "postedAt": "2026-06-13T03:02:41.000Z",
      "avatarUrl": "https://pbs.twimg.com/profile_images/2017804319270309895/TqBzYvKY_normal.png",
      "media": [
        {
          "type": "photo",
          "previewUrl": "https://pbs.twimg.com/media/HKqYWhNa8AIfcmd.jpg",
          "url": "https://pbs.twimg.com/media/HKqYWhNa8AIfcmd.jpg"
        }
      ]
    }
  ],
  "qatar~switzerland": [
    {
      "type": "tweet",
      "url": "https://x.com/TrollFootball/status/2065905126783762609",
      "text": "Qatar vs Switzerland https://t.co/FS5rMprqYQ",
      "author": "TrollFootball",
      "tweetId": "2065905126783762609",
      "likes": 19006,
      "retweets": 1059,
      "engagement": 21271,
      "postedAt": "2026-06-13T21:12:19.000Z",
      "avatarUrl": "https://pbs.twimg.com/profile_images/2007448817789194242/VzLmM12q_normal.jpg",
      "media": [
        {
          "type": "photo",
          "previewUrl": "https://pbs.twimg.com/media/HKuRtlNaIAAceVa.jpg",
          "url": "https://pbs.twimg.com/media/HKuRtlNaIAAceVa.jpg"
        }
      ]
    },
    {
      "type": "tweet",
      "url": "https://x.com/memesvsfootball/status/2065907058877026423",
      "text": "Qatar vs. Switzerland https://t.co/1E1tZjN600",
      "author": "memesvsfootball",
      "tweetId": "2065907058877026423",
      "likes": 476,
      "retweets": 23,
      "engagement": 522,
      "postedAt": "2026-06-13T21:20:00.000Z",
      "avatarUrl": "https://pbs.twimg.com/profile_images/2017804319270309895/TqBzYvKY_normal.png",
      "media": [
        {
          "type": "photo",
          "previewUrl": "https://pbs.twimg.com/media/HKuTF40acAAg1aS.jpg",
          "url": "https://pbs.twimg.com/media/HKuTF40acAAg1aS.jpg"
        }
      ]
    }
  ],
  "brazil~morocco": [
    {
      "type": "tweet",
      "url": "https://x.com/TrollFootball/status/2065953825736081758",
      "text": "Brazil vs Morocco https://t.co/SGVal0Cw8i",
      "author": "TrollFootball",
      "tweetId": "2065953825736081758",
      "likes": 41794,
      "retweets": 2069,
      "engagement": 46074,
      "postedAt": "2026-06-14T00:25:50.000Z",
      "avatarUrl": "https://pbs.twimg.com/profile_images/2007448817789194242/VzLmM12q_normal.jpg",
      "media": [
        {
          "type": "photo",
          "previewUrl": "https://pbs.twimg.com/media/HKu8vSJbwAAJmm6.jpg",
          "url": "https://pbs.twimg.com/media/HKu8vSJbwAAJmm6.jpg"
        }
      ]
    },
    {
      "type": "tweet",
      "url": "https://x.com/Contxtfootball/status/2065954657273327622",
      "text": "Morocco moving like prime Brazil against Brazil is actually wild 😭 https://t.co/5S1HVM75ZQ",
      "author": "Contxtfootball",
      "tweetId": "2065954657273327622",
      "likes": 0,
      "retweets": 0,
      "engagement": 0,
      "postedAt": "2026-06-14T00:29:08.000Z",
      "avatarUrl": "https://pbs.twimg.com/profile_images/1944187419017859073/3KjUtvDF_normal.jpg",
      "media": [
        {
          "type": "video",
          "previewUrl": "https://pbs.twimg.com/amplify_video_thumb/2065954563237007360/img/-EYK0wDdJXrXvBvI.jpg",
          "url": "https://video.twimg.com/amplify_video/2065954563237007360/vid/avc1/1080x1080/BstUcJOLINQJ-R4V.mp4"
        }
      ]
    },
    {
      "type": "tweet",
      "url": "https://x.com/memesvsfootball/status/2065948783033385248",
      "text": "Brazil vs. Morocco https://t.co/Q4HgIkZxzt",
      "author": "memesvsfootball",
      "tweetId": "2065948783033385248",
      "likes": 168,
      "retweets": 6,
      "engagement": 180,
      "postedAt": "2026-06-14T00:05:48.000Z",
      "avatarUrl": "https://pbs.twimg.com/profile_images/2017804319270309895/TqBzYvKY_normal.png",
      "media": [
        {
          "type": "photo",
          "previewUrl": "https://pbs.twimg.com/media/HKu5czYagAA8Q5b.jpg",
          "url": "https://pbs.twimg.com/media/HKu5czYagAA8Q5b.jpg"
        }
      ]
    }
  ],
  "haiti~scotland": [
    {
      "type": "tweet",
      "url": "https://x.com/TrollFootball/status/2065994993387622447",
      "text": "Haiti 🫡 https://t.co/RCN77y8vvn",
      "author": "TrollFootball",
      "tweetId": "2065994993387622447",
      "likes": 47918,
      "retweets": 3703,
      "engagement": 55718,
      "postedAt": "2026-06-14T03:09:25.000Z",
      "avatarUrl": "https://pbs.twimg.com/profile_images/2007448817789194242/VzLmM12q_normal.jpg",
      "media": [
        {
          "type": "photo",
          "previewUrl": "https://pbs.twimg.com/media/HKvjeCGbIAA155h.jpg",
          "url": "https://pbs.twimg.com/media/HKvjeCGbIAA155h.jpg"
        }
      ]
    }
  ],
  "curacao~germany": [
    {
      "type": "tweet",
      "url": "https://x.com/TrollFootball/status/2066244011267096786",
      "text": "Curaçao realising they’re on the same level as 5 times World Champions Brazil.\n\nhttps://t.co/XhDEx5dPfd",
      "author": "TrollFootball",
      "tweetId": "2066244011267096786",
      "likes": 92264,
      "retweets": 5433,
      "engagement": 103562,
      "postedAt": "2026-06-14T19:38:55.000Z",
      "avatarUrl": "https://pbs.twimg.com/profile_images/2007448817789194242/VzLmM12q_normal.jpg",
      "media": [
        {
          "type": "video",
          "previewUrl": "https://pbs.twimg.com/ext_tw_video_thumb/1425496035993047040/pu/img/ZjwqQIkQGpR2iZ_k.jpg",
          "url": "https://video.twimg.com/ext_tw_video/1425496035993047040/pu/vid/640x360/qwrKvFLyrs4i8anO.mp4?tag=12"
        }
      ]
    },
    {
      "type": "tweet",
      "url": "https://x.com/TrollFootball/status/2066237807891460433",
      "text": "How Germans see Curaçao https://t.co/XMAXocnhe0",
      "author": "TrollFootball",
      "tweetId": "2066237807891460433",
      "likes": 80979,
      "retweets": 5482,
      "engagement": 92399,
      "postedAt": "2026-06-14T19:14:16.000Z",
      "avatarUrl": "https://pbs.twimg.com/profile_images/2007448817789194242/VzLmM12q_normal.jpg",
      "media": [
        {
          "type": "photo",
          "previewUrl": "https://pbs.twimg.com/media/HKzARgXbYAA87OD.jpg",
          "url": "https://pbs.twimg.com/media/HKzARgXbYAA87OD.jpg"
        }
      ]
    },
    {
      "type": "tweet",
      "url": "https://x.com/TrollFootball/status/2066240774048772286",
      "text": "Germany doesn't care if you're a whore or a virgin, they just f**k. https://t.co/ozhQ7IMY92",
      "author": "TrollFootball",
      "tweetId": "2066240774048772286",
      "likes": 13694,
      "retweets": 1017,
      "engagement": 15929,
      "postedAt": "2026-06-14T19:26:04.000Z",
      "avatarUrl": "https://pbs.twimg.com/profile_images/2007448817789194242/VzLmM12q_normal.jpg",
      "media": [
        {
          "type": "photo",
          "previewUrl": "https://pbs.twimg.com/media/HKzBpHTb0AAySJT.jpg",
          "url": "https://pbs.twimg.com/media/HKzBpHTb0AAySJT.jpg"
        }
      ]
    },
    {
      "type": "tweet",
      "url": "https://x.com/memesvsfootball/status/2066240526588985853",
      "text": "Germany vs. Curacao match highlights.. \n\nhttps://t.co/sGhrinX0JY",
      "author": "memesvsfootball",
      "tweetId": "2066240526588985853",
      "likes": 49929,
      "retweets": 4394,
      "engagement": 59198,
      "postedAt": "2026-06-14T19:25:05.000Z",
      "avatarUrl": "https://pbs.twimg.com/profile_images/2017804319270309895/TqBzYvKY_normal.png",
      "media": [
        {
          "type": "video",
          "previewUrl": "https://pbs.twimg.com/amplify_video_thumb/2066239914929446912/img/aJOfT8eohyaPvkgm.jpg",
          "url": "https://video.twimg.com/amplify_video/2066239914929446912/vid/avc1/480x720/zVP0F4roYlVYJF30.mp4?tag=14"
        }
      ]
    }
  ],
  "japan~netherlands": [
    {
      "type": "tweet",
      "url": "https://x.com/TrollFootball/status/2066280611640455442",
      "text": "*I am going to bed, this 1st half is boring*\n\n2nd half of Netherlands vs Japan:\n\n https://t.co/Epqa7NMsB0",
      "author": "TrollFootball",
      "tweetId": "2066280611640455442",
      "likes": 85439,
      "retweets": 4689,
      "engagement": 95127,
      "postedAt": "2026-06-14T22:04:22.000Z",
      "avatarUrl": "https://pbs.twimg.com/profile_images/2007448817789194242/VzLmM12q_normal.jpg",
      "media": [
        {
          "type": "video",
          "previewUrl": "https://pbs.twimg.com/amplify_video_thumb/2066280259197296640/img/lRMPBpSqfxy72vfz.jpg",
          "url": "https://video.twimg.com/amplify_video/2066280259197296640/vid/avc1/888x720/4eRcVIzmohOvh7q9.mp4"
        }
      ]
    },
    {
      "type": "tweet",
      "url": "https://x.com/TrollFootball/status/2066305805960532082",
      "text": "Netherlands vs Japan highlights for those who missed it\n\n https://t.co/7hrcvFa18S",
      "author": "TrollFootball",
      "tweetId": "2066305805960532082",
      "likes": 21325,
      "retweets": 1326,
      "engagement": 24135,
      "postedAt": "2026-06-14T23:44:28.000Z",
      "avatarUrl": "https://pbs.twimg.com/profile_images/2007448817789194242/VzLmM12q_normal.jpg",
      "media": [
        {
          "type": "video",
          "previewUrl": "https://pbs.twimg.com/amplify_video_thumb/2066305637378867200/img/5bzckTo3U6SH6uq2.jpg",
          "url": "https://video.twimg.com/amplify_video/2066305637378867200/vid/avc1/858x880/_bss5WnD20Msj7Q9.mp4"
        }
      ]
    },
    {
      "type": "tweet",
      "url": "https://x.com/TrollFootball/status/2066284119299129719",
      "text": "Netherlands vs Japan highlights https://t.co/mmzTqjMfY0",
      "author": "TrollFootball",
      "tweetId": "2066284119299129719",
      "likes": 13483,
      "retweets": 788,
      "engagement": 15141,
      "postedAt": "2026-06-14T22:18:18.000Z",
      "avatarUrl": "https://pbs.twimg.com/profile_images/2007448817789194242/VzLmM12q_normal.jpg",
      "media": [
        {
          "type": "video",
          "previewUrl": "https://pbs.twimg.com/amplify_video_thumb/2066283835957137408/img/ii8Nr7ROLhDmRa86.jpg",
          "url": "https://video.twimg.com/amplify_video/2066283835957137408/vid/avc1/480x360/caDzcVr3m4GtFRHR.mp4"
        }
      ]
    }
  ],
  "ecuador~ivorycoast": [
    {
      "type": "tweet",
      "url": "https://x.com/TrollFootball/status/2066327843987140614",
      "text": "Côte d'Ivoire vs Ecuador https://t.co/AqHNzTVgNM",
      "author": "TrollFootball",
      "tweetId": "2066327843987140614",
      "likes": 9142,
      "retweets": 616,
      "engagement": 10416,
      "postedAt": "2026-06-15T01:12:03.000Z",
      "avatarUrl": "https://pbs.twimg.com/profile_images/2007448817789194242/VzLmM12q_normal.jpg",
      "media": [
        {
          "type": "photo",
          "previewUrl": "https://pbs.twimg.com/media/HK0SJJ-bEAA7kql.jpg",
          "url": "https://pbs.twimg.com/media/HK0SJJ-bEAA7kql.jpg"
        }
      ]
    },
    {
      "type": "tweet",
      "url": "https://x.com/memesvsfootball/status/2066325311399313870",
      "text": "Ivory Coast vs. Ecuador https://t.co/Q0Sv205Tpw",
      "author": "memesvsfootball",
      "tweetId": "2066325311399313870",
      "likes": 44,
      "retweets": 0,
      "engagement": 46,
      "postedAt": "2026-06-15T01:01:59.000Z",
      "avatarUrl": "https://pbs.twimg.com/profile_images/2017804319270309895/TqBzYvKY_normal.png",
      "media": [
        {
          "type": "photo",
          "previewUrl": "https://pbs.twimg.com/media/HK0P3ozbcAAY7rp.jpg",
          "url": "https://pbs.twimg.com/media/HK0P3ozbcAAY7rp.jpg"
        }
      ]
    }
  ],
  "sweden~tunisia": [
    {
      "type": "tweet",
      "url": "https://x.com/TrollFootball/status/2066371599562129799",
      "text": "Gyokeres and Isak against Tunisia\n\nhttps://t.co/J5CKGzenU4",
      "author": "TrollFootball",
      "tweetId": "2066371599562129799",
      "likes": 15135,
      "retweets": 809,
      "engagement": 16806,
      "postedAt": "2026-06-15T04:05:55.000Z",
      "avatarUrl": "https://pbs.twimg.com/profile_images/2007448817789194242/VzLmM12q_normal.jpg",
      "media": [
        {
          "type": "video",
          "previewUrl": "https://pbs.twimg.com/amplify_video_thumb/2066371296599142400/img/cZI7N_rEBd6Poj95.jpg",
          "url": "https://video.twimg.com/amplify_video/2066371296599142400/vid/avc1/888x916/bqlUonH81tGGkv0p.mp4"
        }
      ]
    },
    {
      "type": "tweet",
      "url": "https://x.com/memesvsfootball/status/2066371368648868351",
      "text": "Sweden vs. Tunisia https://t.co/ucxWsGK3XW",
      "author": "memesvsfootball",
      "tweetId": "2066371368648868351",
      "likes": 182,
      "retweets": 5,
      "engagement": 193,
      "postedAt": "2026-06-15T04:05:00.000Z",
      "avatarUrl": "https://pbs.twimg.com/profile_images/2017804319270309895/TqBzYvKY_normal.png",
      "media": [
        {
          "type": "photo",
          "previewUrl": "https://pbs.twimg.com/media/HK05tTJaYAA2LZv.jpg",
          "url": "https://pbs.twimg.com/media/HK05tTJaYAA2LZv.jpg"
        }
      ]
    }
  ],
  "capeverde~spain": [
    {
      "type": "tweet",
      "url": "https://x.com/memesvsfootball/status/2066589073905754581",
      "text": "Spain be like.. https://t.co/p43uEwKmAr",
      "author": "memesvsfootball",
      "tweetId": "2066589073905754581",
      "likes": 791,
      "retweets": 81,
      "engagement": 960,
      "postedAt": "2026-06-15T18:30:05.000Z",
      "avatarUrl": "https://pbs.twimg.com/profile_images/2017804319270309895/TqBzYvKY_normal.png",
      "media": [
        {
          "type": "video",
          "previewUrl": "https://pbs.twimg.com/amplify_video_thumb/2066588870515556352/img/ysKuFHCaFq_APvGL.jpg",
          "url": "https://video.twimg.com/amplify_video/2066588870515556352/vid/avc1/720x1280/JH6nBoWXxf42AToQ.mp4"
        }
      ]
    },
    {
      "type": "tweet",
      "url": "https://x.com/memesvsfootball/status/2066585307357782123",
      "text": "Spain vs. Cape Verde match highlights.. https://t.co/e5LLvp6Tpr",
      "author": "memesvsfootball",
      "tweetId": "2066585307357782123",
      "likes": 175,
      "retweets": 9,
      "engagement": 196,
      "postedAt": "2026-06-15T18:15:07.000Z",
      "avatarUrl": "https://pbs.twimg.com/profile_images/2017804319270309895/TqBzYvKY_normal.png",
      "media": [
        {
          "type": "photo",
          "previewUrl": "https://pbs.twimg.com/media/HK38YNlbMAAWY3P.jpg",
          "url": "https://pbs.twimg.com/media/HK38YNlbMAAWY3P.jpg"
        }
      ]
    }
  ],
  "belgium~egypt": [
    {
      "type": "tweet",
      "url": "https://x.com/TrollFootball/status/2066630912222310454",
      "text": "Me, sleep deprived, trying to explain to my girl how Egypt scored both goals against Belgium and still couldn't win. https://t.co/HvJ5l5rUFa",
      "author": "TrollFootball",
      "tweetId": "2066630912222310454",
      "likes": 14811,
      "retweets": 865,
      "engagement": 16646,
      "postedAt": "2026-06-15T21:16:20.000Z",
      "avatarUrl": "https://pbs.twimg.com/profile_images/2007448817789194242/VzLmM12q_normal.jpg",
      "media": [
        {
          "type": "photo",
          "previewUrl": "https://pbs.twimg.com/media/HK4laY4akAAbO8D.jpg",
          "url": "https://pbs.twimg.com/media/HK4laY4akAAbO8D.jpg"
        }
      ]
    },
    {
      "type": "tweet",
      "url": "https://x.com/TrollFootball/status/2066637361312932125",
      "text": "World Cup broadcast in Belgium https://t.co/uAifIQLvgN",
      "author": "TrollFootball",
      "tweetId": "2066637361312932125",
      "likes": 3910,
      "retweets": 131,
      "engagement": 4214,
      "postedAt": "2026-06-15T21:41:57.000Z",
      "avatarUrl": "https://pbs.twimg.com/profile_images/2007448817789194242/VzLmM12q_normal.jpg",
      "media": [
        {
          "type": "photo",
          "previewUrl": "https://pbs.twimg.com/media/HK4kwLFa8AAMZrn.jpg",
          "url": "https://pbs.twimg.com/media/HK4kwLFa8AAMZrn.jpg"
        }
      ]
    }
  ],
  "saudiarabia~uruguay": [
    {
      "type": "tweet",
      "url": "https://x.com/TrollFootball/status/2066674594833215610",
      "text": "Arteta watching Uruguay get 14 corners and score from none\n https://t.co/NUmfQfUVfQ",
      "author": "TrollFootball",
      "tweetId": "2066674594833215610",
      "likes": 34262,
      "retweets": 2512,
      "engagement": 39426,
      "postedAt": "2026-06-16T00:09:55.000Z",
      "avatarUrl": "https://pbs.twimg.com/profile_images/2007448817789194242/VzLmM12q_normal.jpg",
      "media": [
        {
          "type": "video",
          "previewUrl": "https://pbs.twimg.com/amplify_video_thumb/2059703316653727744/img/vxAGojlnXi8ZrYvL.jpg",
          "url": "https://video.twimg.com/amplify_video/2059703316653727744/vid/avc1/1280x720/gyI7ACbvs8Z4mWBH.mp4"
        }
      ]
    },
    {
      "type": "tweet",
      "url": "https://x.com/TrollFootball/status/2066672474935435620",
      "text": "Saudi Arabia against Uruguay https://t.co/rJvZivureI",
      "author": "TrollFootball",
      "tweetId": "2066672474935435620",
      "likes": 10310,
      "retweets": 646,
      "engagement": 11869,
      "postedAt": "2026-06-16T00:01:29.000Z",
      "avatarUrl": "https://pbs.twimg.com/profile_images/2007448817789194242/VzLmM12q_normal.jpg",
      "media": [
        {
          "type": "photo",
          "previewUrl": "https://pbs.twimg.com/media/HK5Loc-aQAAwA-3.jpg",
          "url": "https://pbs.twimg.com/media/HK5Loc-aQAAwA-3.jpg"
        }
      ]
    }
  ],
  "iran~newzealand": [
    {
      "type": "tweet",
      "url": "https://x.com/TrollFootball/status/2066718228735504876",
      "text": "A moment of silence for those who missed Iran vs New Zealand https://t.co/mITHnPRYO6",
      "author": "TrollFootball",
      "tweetId": "2066718228735504876",
      "likes": 50394,
      "retweets": 3379,
      "engagement": 57550,
      "postedAt": "2026-06-16T03:03:18.000Z",
      "avatarUrl": "https://pbs.twimg.com/profile_images/2007448817789194242/VzLmM12q_normal.jpg",
      "media": [
        {
          "type": "photo",
          "previewUrl": "https://pbs.twimg.com/media/HK51MgCb0AAFkZA.jpg",
          "url": "https://pbs.twimg.com/media/HK51MgCb0AAFkZA.jpg"
        }
      ]
    },
    {
      "type": "tweet",
      "url": "https://x.com/memesvsfootball/status/2066719915139289303",
      "text": "Iran vs. New Zealand match be like.. https://t.co/WOxppre09H",
      "author": "memesvsfootball",
      "tweetId": "2066719915139289303",
      "likes": 440,
      "retweets": 19,
      "engagement": 479,
      "postedAt": "2026-06-16T03:10:00.000Z",
      "avatarUrl": "https://pbs.twimg.com/profile_images/2017804319270309895/TqBzYvKY_normal.png",
      "media": [
        {
          "type": "photo",
          "previewUrl": "https://pbs.twimg.com/media/HK52dqIa0AAz_-I.jpg",
          "url": "https://pbs.twimg.com/media/HK52dqIa0AAz_-I.jpg"
        }
      ]
    }
  ],
  "france~senegal": [
    {
      "type": "tweet",
      "url": "https://x.com/TrollFootball/status/2067005350155563469",
      "text": "Olise and Mbappe against Senegal https://t.co/6AJNleNAPk",
      "author": "TrollFootball",
      "tweetId": "2067005350155563469",
      "likes": 35732,
      "retweets": 1870,
      "engagement": 39569,
      "postedAt": "2026-06-16T22:04:13.000Z",
      "avatarUrl": "https://pbs.twimg.com/profile_images/2007448817789194242/VzLmM12q_normal.jpg",
      "media": [
        {
          "type": "video",
          "previewUrl": "https://pbs.twimg.com/amplify_video_thumb/2066994447750230016/img/yT4ZAg2xQPSYEiYP.jpg",
          "url": "https://video.twimg.com/amplify_video/2066994447750230016/vid/avc1/720x858/l2HuZkiOgVjqas-I.mp4"
        }
      ]
    },
    {
      "type": "tweet",
      "url": "https://x.com/TrollFootball/status/2066997062793920935",
      "text": "Mbappe at France is next level https://t.co/21TxCxlwVu",
      "author": "TrollFootball",
      "tweetId": "2066997062793920935",
      "likes": 21482,
      "retweets": 877,
      "engagement": 23347,
      "postedAt": "2026-06-16T21:31:17.000Z",
      "avatarUrl": "https://pbs.twimg.com/profile_images/2007448817789194242/VzLmM12q_normal.jpg",
      "media": [
        {
          "type": "photo",
          "previewUrl": "https://pbs.twimg.com/media/HK9yA_UbkAEDH7h.jpg",
          "url": "https://pbs.twimg.com/media/HK9yA_UbkAEDH7h.jpg"
        }
      ]
    },
    {
      "type": "tweet",
      "url": "https://x.com/TrollFootball/status/2066992247753834759",
      "text": "\"Bro you can only celebrate your country’s goals\"\n\nMe celebrating Mbappe’s worldie against Senegal (I’ve trolled him all season):\n https://t.co/udLhDZLm6z",
      "author": "TrollFootball",
      "tweetId": "2066992247753834759",
      "likes": 14927,
      "retweets": 810,
      "engagement": 16627,
      "postedAt": "2026-06-16T21:12:09.000Z",
      "avatarUrl": "https://pbs.twimg.com/profile_images/2007448817789194242/VzLmM12q_normal.jpg",
      "media": [
        {
          "type": "video",
          "previewUrl": "https://pbs.twimg.com/ext_tw_video_thumb/1904405595857297408/pu/img/Yca5vx0IW9LnUvaU.jpg",
          "url": "https://video.twimg.com/ext_tw_video/1904405595857297408/pu/vid/avc1/930x720/pd5i450OalJkLxh4.mp4?tag=12"
        }
      ]
    }
  ],
  "iraq~norway": [
    {
      "type": "tweet",
      "url": "https://x.com/TrollFootball/status/2067034887929098717",
      "text": "Norway crushes Iraq https://t.co/3rtE6djliH",
      "author": "TrollFootball",
      "tweetId": "2067034887929098717",
      "likes": 8093,
      "retweets": 303,
      "engagement": 8780,
      "postedAt": "2026-06-17T00:01:35.000Z",
      "avatarUrl": "https://pbs.twimg.com/profile_images/2007448817789194242/VzLmM12q_normal.jpg",
      "media": [
        {
          "type": "photo",
          "previewUrl": "https://pbs.twimg.com/media/HK-VQU6aMAArgTJ.jpg",
          "url": "https://pbs.twimg.com/media/HK-VQU6aMAArgTJ.jpg"
        }
      ]
    },
    {
      "type": "tweet",
      "url": "https://x.com/memesvsfootball/status/2067034495098982722",
      "text": "Iraq vs. Norway https://t.co/Lj45Oyc4My",
      "author": "memesvsfootball",
      "tweetId": "2067034495098982722",
      "likes": 113,
      "retweets": 9,
      "engagement": 131,
      "postedAt": "2026-06-17T00:00:01.000Z",
      "avatarUrl": "https://pbs.twimg.com/profile_images/2017804319270309895/TqBzYvKY_normal.png",
      "media": [
        {
          "type": "photo",
          "previewUrl": "https://pbs.twimg.com/media/HK-Us8YbkAAFMeI.jpg",
          "url": "https://pbs.twimg.com/media/HK-Us8YbkAAFMeI.jpg"
        }
      ]
    }
  ],
  "algeria~argentina": [
    {
      "type": "tweet",
      "url": "https://x.com/TrollFootball/status/2067097476956635423",
      "text": "Mbappe: 2 goals\nHaaland: 2 goals\nMessi: 3 goals\n\nNeymar: https://t.co/GwOcn0eQVX",
      "author": "TrollFootball",
      "tweetId": "2067097476956635423",
      "likes": 22663,
      "retweets": 1146,
      "engagement": 25194,
      "postedAt": "2026-06-17T04:10:17.000Z",
      "avatarUrl": "https://pbs.twimg.com/profile_images/2007448817789194242/VzLmM12q_normal.jpg",
      "media": [
        {
          "type": "photo",
          "previewUrl": "https://pbs.twimg.com/media/HK_OE4WbEAAkPuD.jpg",
          "url": "https://pbs.twimg.com/media/HK_OE4WbEAAkPuD.jpg"
        }
      ]
    },
    {
      "type": "tweet",
      "url": "https://x.com/TrollFootball/status/2067088043190911260",
      "text": "Ronaldo at the World Cup camp watching Messi score a hattrick https://t.co/Pz0YuSN8PA",
      "author": "TrollFootball",
      "tweetId": "2067088043190911260",
      "likes": 15853,
      "retweets": 1112,
      "engagement": 18193,
      "postedAt": "2026-06-17T03:32:48.000Z",
      "avatarUrl": "https://pbs.twimg.com/profile_images/2007448817789194242/VzLmM12q_normal.jpg",
      "media": [
        {
          "type": "video",
          "previewUrl": "https://pbs.twimg.com/ext_tw_video_thumb/1552208441455812608/pu/img/UwfF6Reex8opOKhZ.jpg",
          "url": "https://video.twimg.com/ext_tw_video/1552208441455812608/pu/vid/728x470/xpBaMrmAUpCcV48A.mp4?tag=12"
        }
      ]
    },
    {
      "type": "tweet",
      "url": "https://x.com/TrollFootball/status/2067082323913552047",
      "text": "Americans thinking Messi just became the first US international to score a World Cup hattrick\n\n https://t.co/BLXzCSfnOc",
      "author": "TrollFootball",
      "tweetId": "2067082323913552047",
      "likes": 11758,
      "retweets": 458,
      "engagement": 12742,
      "postedAt": "2026-06-17T03:10:05.000Z",
      "avatarUrl": "https://pbs.twimg.com/profile_images/2007448817789194242/VzLmM12q_normal.jpg",
      "media": [
        {
          "type": "video",
          "previewUrl": "https://pbs.twimg.com/amplify_video_thumb/2067081975618469888/img/-Hmn2mtrZEdAsEdA.jpg",
          "url": "https://video.twimg.com/amplify_video/2067081975618469888/vid/avc1/720x960/9U_1cvDM_PulujzH.mp4"
        }
      ]
    }
  ],
  "austria~jordan": [
    {
      "type": "tweet",
      "url": "https://x.com/TrollFootball/status/2067127982075113867",
      "text": "Austria vs Jordan https://t.co/pfhWS1Kwnd",
      "author": "TrollFootball",
      "tweetId": "2067127982075113867",
      "likes": 4660,
      "retweets": 170,
      "engagement": 5063,
      "postedAt": "2026-06-17T06:11:30.000Z",
      "avatarUrl": "https://pbs.twimg.com/profile_images/2007448817789194242/VzLmM12q_normal.jpg",
      "media": [
        {
          "type": "photo",
          "previewUrl": "https://pbs.twimg.com/media/HK_p5A2acAA6oAD.jpg",
          "url": "https://pbs.twimg.com/media/HK_p5A2acAA6oAD.jpg"
        }
      ]
    }
  ],
  "congodr~portugal": [
    {
      "type": "tweet",
      "url": "https://x.com/TrollFootball/status/2067336554536915282",
      "text": "Why is everyone making fun of Ronaldo? As an Aussie, my GOAT got the best rating https://t.co/TJWFdTMYoh",
      "author": "TrollFootball",
      "tweetId": "2067336554536915282",
      "likes": 38566,
      "retweets": 3543,
      "engagement": 46279,
      "postedAt": "2026-06-17T20:00:18.000Z",
      "avatarUrl": "https://pbs.twimg.com/profile_images/2007448817789194242/VzLmM12q_normal.jpg",
      "media": [
        {
          "type": "photo",
          "previewUrl": "https://pbs.twimg.com/media/HLCnNsqawAAOcO3.jpg",
          "url": "https://pbs.twimg.com/media/HLCnNsqawAAOcO3.jpg"
        }
      ]
    },
    {
      "type": "tweet",
      "url": "https://x.com/TrollFootball/status/2067327820800684332",
      "text": "Portugal vs DR Congo https://t.co/8g8OaD14cH",
      "author": "TrollFootball",
      "tweetId": "2067327820800684332",
      "likes": 26493,
      "retweets": 3556,
      "engagement": 34270,
      "postedAt": "2026-06-17T19:25:36.000Z",
      "avatarUrl": "https://pbs.twimg.com/profile_images/2007448817789194242/VzLmM12q_normal.jpg",
      "media": [
        {
          "type": "video",
          "previewUrl": "https://pbs.twimg.com/amplify_video_thumb/2067327367782240256/img/--zIvBQvcnji9qU7.jpg",
          "url": "https://video.twimg.com/amplify_video/2067327367782240256/vid/avc1/720x1280/sXJibfHWFxjed0Xa.mp4"
        }
      ]
    },
    {
      "type": "tweet",
      "url": "https://x.com/TrollFootball/status/2067331757868036534",
      "text": "Mbappe: 2 goals\nHaaland: 2 goals\nMessi: 3 goals\nRonaldo: 2 hydration breaks https://t.co/7jnQG1dtWu",
      "author": "TrollFootball",
      "tweetId": "2067331757868036534",
      "likes": 19248,
      "retweets": 1954,
      "engagement": 23552,
      "postedAt": "2026-06-17T19:41:14.000Z",
      "avatarUrl": "https://pbs.twimg.com/profile_images/2007448817789194242/VzLmM12q_normal.jpg",
      "media": [
        {
          "type": "photo",
          "previewUrl": "https://pbs.twimg.com/media/HLCjN3obkAAWMfm.png",
          "url": "https://pbs.twimg.com/media/HLCjN3obkAAWMfm.png"
        }
      ]
    },
    {
      "type": "tweet",
      "url": "https://x.com/memesvsfootball/status/2067340263299919950",
      "text": "Ronaldo be like.. \n\nhttps://t.co/IYB6dbJdNc",
      "author": "memesvsfootball",
      "tweetId": "2067340263299919950",
      "likes": 109,
      "retweets": 8,
      "engagement": 127,
      "postedAt": "2026-06-17T20:15:02.000Z",
      "avatarUrl": "https://pbs.twimg.com/profile_images/2017804319270309895/TqBzYvKY_normal.png",
      "media": [
        {
          "type": "video",
          "previewUrl": "https://pbs.twimg.com/amplify_video_thumb/2067338392334192640/img/q0_Kg3uXCfSKScvy.jpg",
          "url": "https://video.twimg.com/amplify_video/2067338392334192640/vid/avc1/360x640/5Gc-B59szbs6p4nv.mp4?tag=14"
        }
      ]
    }
  ],
  "croatia~england": [
    {
      "type": "tweet",
      "url": "https://x.com/TrollFootball/status/2067367954480791647",
      "text": "England vs Croatia https://t.co/drXJI5uG2j",
      "author": "TrollFootball",
      "tweetId": "2067367954480791647",
      "likes": 20396,
      "retweets": 976,
      "engagement": 22436,
      "postedAt": "2026-06-17T22:05:04.000Z",
      "avatarUrl": "https://pbs.twimg.com/profile_images/2007448817789194242/VzLmM12q_normal.jpg",
      "media": [
        {
          "type": "photo",
          "previewUrl": "https://pbs.twimg.com/media/HLDEJOubYAANYZG.jpg",
          "url": "https://pbs.twimg.com/media/HLDEJOubYAANYZG.jpg"
        }
      ]
    },
    {
      "type": "tweet",
      "url": "https://x.com/memesvsfootball/status/2067372990745165913",
      "text": "England vs. Croatia match highlights.. https://t.co/9IsPhLAEEW",
      "author": "memesvsfootball",
      "tweetId": "2067372990745165913",
      "likes": 275,
      "retweets": 14,
      "engagement": 305,
      "postedAt": "2026-06-17T22:25:05.000Z",
      "avatarUrl": "https://pbs.twimg.com/profile_images/2017804319270309895/TqBzYvKY_normal.png",
      "media": [
        {
          "type": "photo",
          "previewUrl": "https://pbs.twimg.com/media/HLDIjxiasAA9aA_.jpg",
          "url": "https://pbs.twimg.com/media/HLDIjxiasAA9aA_.jpg"
        }
      ]
    }
  ],
  "ghana~panama": [
    {
      "type": "tweet",
      "url": "https://x.com/TrollFootball/status/2067416357721997762",
      "text": "Ghana vs Panama https://t.co/HgNHzRx7WL",
      "author": "TrollFootball",
      "tweetId": "2067416357721997762",
      "likes": 27399,
      "retweets": 2845,
      "engagement": 33241,
      "postedAt": "2026-06-18T01:17:25.000Z",
      "avatarUrl": "https://pbs.twimg.com/profile_images/2007448817789194242/VzLmM12q_normal.jpg",
      "media": [
        {
          "type": "video",
          "previewUrl": "https://pbs.twimg.com/amplify_video_thumb/2067416088498077696/img/85aFkjKONTOnLokZ.jpg",
          "url": "https://video.twimg.com/amplify_video/2067416088498077696/vid/avc1/1080x1638/pnVJI8-N8LL5IeCo.mp4"
        }
      ]
    }
  ],
  "colombia~uzbekistan": [
    {
      "type": "tweet",
      "url": "https://x.com/TrollFootball/status/2067466142223155564",
      "text": "The cameraman of the Colombia vs Uzbekistan game\n https://t.co/djb1cnYwSo",
      "author": "TrollFootball",
      "tweetId": "2067466142223155564",
      "likes": 8188,
      "retweets": 503,
      "engagement": 9264,
      "postedAt": "2026-06-18T04:35:14.000Z",
      "avatarUrl": "https://pbs.twimg.com/profile_images/2007448817789194242/VzLmM12q_normal.jpg",
      "media": [
        {
          "type": "video",
          "previewUrl": "https://pbs.twimg.com/amplify_video_thumb/2008768610945159168/img/9pXGSDH890gu-V9o.jpg",
          "url": "https://video.twimg.com/amplify_video/2008768610945159168/vid/avc1/752x416/7L4wYp19wbYwAqPx.mp4"
        }
      ]
    }
  ],
  "czechia~southafrica": [
    {
      "type": "tweet",
      "url": "https://x.com/TrollFootball/status/2067668967720931630",
      "text": "Czechia vs South Africa https://t.co/u4P3tCbun7",
      "author": "TrollFootball",
      "tweetId": "2067668967720931630",
      "likes": 17197,
      "retweets": 626,
      "engagement": 18547,
      "postedAt": "2026-06-18T18:01:11.000Z",
      "avatarUrl": "https://pbs.twimg.com/profile_images/2007448817789194242/VzLmM12q_normal.jpg",
      "media": [
        {
          "type": "photo",
          "previewUrl": "https://pbs.twimg.com/media/HLHV8UZa4AAHeIc.jpg",
          "url": "https://pbs.twimg.com/media/HLHV8UZa4AAHeIc.jpg"
        }
      ]
    },
    {
      "type": "tweet",
      "url": "https://x.com/TrollFootball/status/2067673558889972117",
      "text": "Arteta at home watching Czechia ball https://t.co/WWWCYYAJUY",
      "author": "TrollFootball",
      "tweetId": "2067673558889972117",
      "likes": 6575,
      "retweets": 239,
      "engagement": 7109,
      "postedAt": "2026-06-18T18:19:26.000Z",
      "avatarUrl": "https://pbs.twimg.com/profile_images/2007448817789194242/VzLmM12q_normal.jpg",
      "media": [
        {
          "type": "video",
          "previewUrl": "https://pbs.twimg.com/amplify_video_thumb/2067673278362402816/img/mmEScJVrqU5OVsKI.jpg",
          "url": "https://video.twimg.com/amplify_video/2067673278362402816/vid/avc1/1228x720/nMQdHYFn-Lk7DHjM.mp4"
        }
      ]
    },
    {
      "type": "tweet",
      "url": "https://x.com/Contxtfootball/status/2067670639838646479",
      "text": "South Africa when it comes to taking cards https://t.co/sQIDEuJqQD",
      "author": "Contxtfootball",
      "tweetId": "2067670639838646479",
      "likes": 0,
      "retweets": 0,
      "engagement": 0,
      "postedAt": "2026-06-18T18:07:50.000Z",
      "avatarUrl": "https://pbs.twimg.com/profile_images/1944187419017859073/3KjUtvDF_normal.jpg",
      "media": [
        {
          "type": "video",
          "previewUrl": "https://pbs.twimg.com/ext_tw_video_thumb/1904112162378756096/pu/img/a3tqa1nmQ5njjKNn.jpg",
          "url": "https://video.twimg.com/ext_tw_video/1904112162378756096/pu/vid/avc1/718x646/gT_U76HtQ9mgyhx9.mp4?tag=12"
        }
      ]
    }
  ],
  "canada~qatar": [
    {
      "type": "tweet",
      "url": "https://x.com/TrollFootball/status/2067760631550484550",
      "text": "Canada vs Qatar https://t.co/hVhq809cYN",
      "author": "TrollFootball",
      "tweetId": "2067760631550484550",
      "likes": 44799,
      "retweets": 4304,
      "engagement": 54027,
      "postedAt": "2026-06-19T00:05:26.000Z",
      "avatarUrl": "https://pbs.twimg.com/profile_images/2007448817789194242/VzLmM12q_normal.jpg",
      "media": [
        {
          "type": "video",
          "previewUrl": "https://pbs.twimg.com/amplify_video_thumb/2067760476411539457/img/TQxqhNxwFcg5nMXV.jpg",
          "url": "https://video.twimg.com/amplify_video/2067760476411539457/vid/avc1/1080x1404/uTBQU9LKGd1tYGvd.mp4"
        }
      ]
    }
  ],
  "mexico~southkorea": [
    {
      "type": "tweet",
      "url": "https://x.com/TrollFootball/status/2067807469016158712",
      "text": "South Korea’s worst nightmare https://t.co/JMr7fuxu1D",
      "author": "TrollFootball",
      "tweetId": "2067807469016158712",
      "likes": 75187,
      "retweets": 3991,
      "engagement": 84392,
      "postedAt": "2026-06-19T03:11:33.000Z",
      "avatarUrl": "https://pbs.twimg.com/profile_images/2007448817789194242/VzLmM12q_normal.jpg",
      "media": [
        {
          "type": "photo",
          "previewUrl": "https://pbs.twimg.com/media/HLJSivCbEAAYSA9.jpg",
          "url": "https://pbs.twimg.com/media/HLJSivCbEAAYSA9.jpg"
        }
      ]
    },
    {
      "type": "tweet",
      "url": "https://x.com/TrollFootball/status/2067804828206846374",
      "text": "North Koreans when Kim Jong Un tells them South Korea lost 100-0 to Mexico https://t.co/DKTinIIm2G",
      "author": "TrollFootball",
      "tweetId": "2067804828206846374",
      "likes": 59704,
      "retweets": 2048,
      "engagement": 63946,
      "postedAt": "2026-06-19T03:01:03.000Z",
      "avatarUrl": "https://pbs.twimg.com/profile_images/2007448817789194242/VzLmM12q_normal.jpg",
      "media": [
        {
          "type": "video",
          "previewUrl": "https://pbs.twimg.com/amplify_video_thumb/2065512967400042497/img/57zICyCcJhnIySQB.jpg",
          "url": "https://video.twimg.com/amplify_video/2065512967400042497/vid/avc1/576x322/zyvFczXA2aXmQMGf.mp4"
        }
      ]
    },
    {
      "type": "tweet",
      "url": "https://x.com/memesvsfootball/status/2067804684451303649",
      "text": "Mexico vs. South Korea in World Cup https://t.co/pQo4Amcm8O",
      "author": "memesvsfootball",
      "tweetId": "2067804684451303649",
      "likes": 133,
      "retweets": 10,
      "engagement": 155,
      "postedAt": "2026-06-19T03:00:29.000Z",
      "avatarUrl": "https://pbs.twimg.com/profile_images/2017804319270309895/TqBzYvKY_normal.png",
      "media": [
        {
          "type": "photo",
          "previewUrl": "https://pbs.twimg.com/media/HLJRZQxacAERm5Z.jpg",
          "url": "https://pbs.twimg.com/media/HLJRZQxacAERm5Z.jpg"
        }
      ]
    }
  ],
  "australia~unitedstates": [
    {
      "type": "tweet",
      "url": "https://x.com/TrollFootball/status/2068077388186124790",
      "text": "USA vs Australia\n\n https://t.co/AapHMXA1eQ",
      "author": "TrollFootball",
      "tweetId": "2068077388186124790",
      "likes": 6213,
      "retweets": 433,
      "engagement": 7152,
      "postedAt": "2026-06-19T21:04:07.000Z",
      "avatarUrl": "https://pbs.twimg.com/profile_images/2007448817789194242/VzLmM12q_normal.jpg",
      "media": [
        {
          "type": "video",
          "previewUrl": "https://pbs.twimg.com/amplify_video_thumb/2068077165556678656/img/qHOYlxYI-HjsIIlT.jpg",
          "url": "https://video.twimg.com/amplify_video/2068077165556678656/vid/avc1/1080x652/8IzbtYiNMFqMnpq6.mp4"
        }
      ]
    }
  ],
  "morocco~scotland": [
    {
      "type": "tweet",
      "url": "https://x.com/TrollFootball/status/2068125595008213294",
      "text": "Morocco vs Scotland\n\n https://t.co/Vvk9zE3ygm",
      "author": "TrollFootball",
      "tweetId": "2068125595008213294",
      "likes": 4104,
      "retweets": 116,
      "engagement": 4362,
      "postedAt": "2026-06-20T00:15:40.000Z",
      "avatarUrl": "https://pbs.twimg.com/profile_images/2007448817789194242/VzLmM12q_normal.jpg",
      "media": [
        {
          "type": "video",
          "previewUrl": "https://pbs.twimg.com/amplify_video_thumb/2068125344125820928/img/6oKKURJhXHG6Y9pt.jpg",
          "url": "https://video.twimg.com/amplify_video/2068125344125820928/vid/avc1/1128x720/ImoEHr0yLA9DZLnN.mp4"
        }
      ]
    }
  ],
  "brazil~haiti": [
    {
      "type": "tweet",
      "url": "https://x.com/TrollFootball/status/2068159716405240104",
      "text": "Brazil vs Haiti https://t.co/rMinTqbohm",
      "author": "TrollFootball",
      "tweetId": "2068159716405240104",
      "likes": 15945,
      "retweets": 810,
      "engagement": 17689,
      "postedAt": "2026-06-20T02:31:15.000Z",
      "avatarUrl": "https://pbs.twimg.com/profile_images/2007448817789194242/VzLmM12q_normal.jpg",
      "media": [
        {
          "type": "video",
          "previewUrl": "https://pbs.twimg.com/amplify_video_thumb/2068158917587386368/img/J8sN_pGddq9-LOdS.jpg",
          "url": "https://video.twimg.com/amplify_video/2068158917587386368/vid/avc1/480x480/DqczEa8FHUioYLXD.mp4"
        }
      ]
    }
  ],
  "paraguay~turkiye": [
    {
      "type": "tweet",
      "url": "https://x.com/TrollFootball/status/2068198617593397554",
      "text": "The only thing Türkiye can win https://t.co/b4OjNhcYCO",
      "author": "TrollFootball",
      "tweetId": "2068198617593397554",
      "likes": 234656,
      "retweets": 17123,
      "engagement": 272594,
      "postedAt": "2026-06-20T05:05:50.000Z",
      "avatarUrl": "https://pbs.twimg.com/profile_images/2007448817789194242/VzLmM12q_normal.jpg",
      "media": [
        {
          "type": "photo",
          "previewUrl": "https://pbs.twimg.com/media/HLO0r-HbUAADuVS.jpg",
          "url": "https://pbs.twimg.com/media/HLO0r-HbUAADuVS.jpg"
        }
      ]
    },
    {
      "type": "tweet",
      "url": "https://x.com/TrollFootball/status/2068209116498268430",
      "text": "Türkiye at the 2026 World Cup\n\n https://t.co/WzXuAAYiOx",
      "author": "TrollFootball",
      "tweetId": "2068209116498268430",
      "likes": 27072,
      "retweets": 1843,
      "engagement": 31207,
      "postedAt": "2026-06-20T05:47:33.000Z",
      "avatarUrl": "https://pbs.twimg.com/profile_images/2007448817789194242/VzLmM12q_normal.jpg",
      "media": [
        {
          "type": "video",
          "previewUrl": "https://pbs.twimg.com/amplify_video_thumb/2068208746162278400/img/T6avOm7d-tCcsi8H.jpg",
          "url": "https://video.twimg.com/amplify_video/2068208746162278400/vid/avc1/1280x720/FMEFgO_6w4JRBKiI.mp4"
        }
      ]
    },
    {
      "type": "tweet",
      "url": "https://x.com/memesvsfootball/status/2068223573106536815",
      "text": "Türkiye.. 🇹🇷💔\n\nhttps://t.co/hOunnBOrQa",
      "author": "memesvsfootball",
      "tweetId": "2068223573106536815",
      "likes": 15475,
      "retweets": 1337,
      "engagement": 18404,
      "postedAt": "2026-06-20T06:45:00.000Z",
      "avatarUrl": "https://pbs.twimg.com/profile_images/2017804319270309895/TqBzYvKY_normal.png",
      "media": [
        {
          "type": "video",
          "previewUrl": "https://pbs.twimg.com/amplify_video_thumb/2068222545351114752/img/J_2bKe8-O1vu3Pkv.jpg",
          "url": "https://video.twimg.com/amplify_video/2068222545351114752/vid/avc1/750x600/sj7fPLDrnJi8gnd7.mp4?tag=14"
        }
      ]
    }
  ],
  "netherlands~sweden": [
    {
      "type": "tweet",
      "url": "https://x.com/TrollFootball/status/2068416868629774544",
      "text": "Netherlands vs Sweden https://t.co/2w8bWTb9af",
      "author": "TrollFootball",
      "tweetId": "2068416868629774544",
      "likes": 29798,
      "retweets": 2069,
      "engagement": 34078,
      "postedAt": "2026-06-20T19:33:05.000Z",
      "avatarUrl": "https://pbs.twimg.com/profile_images/2007448817789194242/VzLmM12q_normal.jpg",
      "media": [
        {
          "type": "photo",
          "previewUrl": "https://pbs.twimg.com/media/HLR-LINacAAVFpx.jpg",
          "url": "https://pbs.twimg.com/media/HLR-LINacAAVFpx.jpg"
        }
      ]
    }
  ],
  "germany~ivorycoast": [
    {
      "type": "tweet",
      "url": "https://x.com/TrollFootball/status/2068457379822440549",
      "text": "Germany's man of the match https://t.co/badQrKuykA",
      "author": "TrollFootball",
      "tweetId": "2068457379822440549",
      "likes": 26512,
      "retweets": 2084,
      "engagement": 31148,
      "postedAt": "2026-06-20T22:14:04.000Z",
      "avatarUrl": "https://pbs.twimg.com/profile_images/2007448817789194242/VzLmM12q_normal.jpg",
      "media": [
        {
          "type": "photo",
          "previewUrl": "https://pbs.twimg.com/media/HLSizxPbwAAz7x7.jpg",
          "url": "https://pbs.twimg.com/media/HLSizxPbwAAz7x7.jpg"
        }
      ]
    },
    {
      "type": "tweet",
      "url": "https://x.com/TrollFootball/status/2068454721652990034",
      "text": "Germany vs Côte d'Ivoire https://t.co/fa9ieY20wk",
      "author": "TrollFootball",
      "tweetId": "2068454721652990034",
      "likes": 26850,
      "retweets": 1336,
      "engagement": 29628,
      "postedAt": "2026-06-20T22:03:30.000Z",
      "avatarUrl": "https://pbs.twimg.com/profile_images/2007448817789194242/VzLmM12q_normal.jpg",
      "media": [
        {
          "type": "photo",
          "previewUrl": "https://pbs.twimg.com/media/HLSgkNDasAEZ1X9.jpg",
          "url": "https://pbs.twimg.com/media/HLSgkNDasAEZ1X9.jpg"
        }
      ]
    }
  ],
  "curacao~ecuador": [
    {
      "type": "tweet",
      "url": "https://x.com/TrollFootball/status/2068514931209904529",
      "text": "Ecuador vs Curacao\n\n https://t.co/81NFkexhxd",
      "author": "TrollFootball",
      "tweetId": "2068514931209904529",
      "likes": 61588,
      "retweets": 4311,
      "engagement": 70493,
      "postedAt": "2026-06-21T02:02:45.000Z",
      "avatarUrl": "https://pbs.twimg.com/profile_images/2007448817789194242/VzLmM12q_normal.jpg",
      "media": [
        {
          "type": "video",
          "previewUrl": "https://pbs.twimg.com/amplify_video_thumb/2068514765459398656/img/Yiok1P1LsiDBUj59.jpg",
          "url": "https://video.twimg.com/amplify_video/2068514765459398656/vid/avc1/888x964/vLeZuqIXEDcHInlc.mp4"
        }
      ]
    },
    {
      "type": "tweet",
      "url": "https://x.com/TrollFootball/status/2068518545101856790",
      "text": "Legends who didn’t go to sleep after Germany’s game and stayed up to watch Eloy Room’s masterclass against Ecuador\n\nhttps://t.co/tLnoFpLO56",
      "author": "TrollFootball",
      "tweetId": "2068518545101856790",
      "likes": 4788,
      "retweets": 226,
      "engagement": 5276,
      "postedAt": "2026-06-21T02:17:07.000Z",
      "avatarUrl": "https://pbs.twimg.com/profile_images/2007448817789194242/VzLmM12q_normal.jpg",
      "media": [
        {
          "type": "video",
          "previewUrl": "https://pbs.twimg.com/amplify_video_thumb/2066837609226088448/img/iWPS_02SjxFnw4oZ.jpg",
          "url": "https://video.twimg.com/amplify_video/2066837609226088448/vid/avc1/828x464/AoMphh7g4BAPCm4u.mp4"
        }
      ]
    },
    {
      "type": "tweet",
      "url": "https://x.com/memesvsfootball/status/2068530796793839833",
      "text": "Ecuador vs. Curacao\n\nhttps://t.co/ptese2DK4v",
      "author": "memesvsfootball",
      "tweetId": "2068530796793839833",
      "likes": 6686,
      "retweets": 563,
      "engagement": 7853,
      "postedAt": "2026-06-21T03:05:48.000Z",
      "avatarUrl": "https://pbs.twimg.com/profile_images/2017804319270309895/TqBzYvKY_normal.png",
      "media": [
        {
          "type": "video",
          "previewUrl": "https://pbs.twimg.com/amplify_video_thumb/2068530431642005504/img/agzR6iMVxVuzimSp.jpg",
          "url": "https://video.twimg.com/amplify_video/2068530431642005504/vid/avc1/540x360/Uz7EvnEYtsCaxs4E.mp4?tag=14"
        }
      ]
    }
  ],
  "japan~tunisia": [
    {
      "type": "tweet",
      "url": "https://x.com/TrollFootball/status/2068577488763232505",
      "text": "Japan vs Tunisia match highlights https://t.co/pwyJzsBknh",
      "author": "TrollFootball",
      "tweetId": "2068577488763232505",
      "likes": 65421,
      "retweets": 4902,
      "engagement": 75719,
      "postedAt": "2026-06-21T06:11:20.000Z",
      "avatarUrl": "https://pbs.twimg.com/profile_images/2007448817789194242/VzLmM12q_normal.jpg",
      "media": [
        {
          "type": "video",
          "previewUrl": "https://pbs.twimg.com/amplify_video_thumb/2068577369452122112/img/hFk1Pwzkbttiohhv.jpg",
          "url": "https://video.twimg.com/amplify_video/2068577369452122112/vid/avc1/888x1190/NZWT0uGFAde9oWoV.mp4"
        }
      ]
    },
    {
      "type": "tweet",
      "url": "https://x.com/TrollFootball/status/2068596627443716412",
      "text": "Tunisia at the 2026 World Cup https://t.co/8qu2dnbuqp",
      "author": "TrollFootball",
      "tweetId": "2068596627443716412",
      "likes": 17715,
      "retweets": 744,
      "engagement": 19290,
      "postedAt": "2026-06-21T07:27:23.000Z",
      "avatarUrl": "https://pbs.twimg.com/profile_images/2007448817789194242/VzLmM12q_normal.jpg",
      "media": [
        {
          "type": "photo",
          "previewUrl": "https://pbs.twimg.com/media/HLUZtb4aIAA8Xgm.jpg",
          "url": "https://pbs.twimg.com/media/HLUZtb4aIAA8Xgm.jpg"
        }
      ]
    }
  ],
  "saudiarabia~spain": [
    {
      "type": "tweet",
      "url": "https://x.com/TrollFootball/status/2068759769759023341",
      "text": "Spain vs Saudi Arabia https://t.co/rUR8D5xEn4",
      "author": "TrollFootball",
      "tweetId": "2068759769759023341",
      "likes": 39990,
      "retweets": 2006,
      "engagement": 44198,
      "postedAt": "2026-06-21T18:15:39.000Z",
      "avatarUrl": "https://pbs.twimg.com/profile_images/2007448817789194242/VzLmM12q_normal.jpg",
      "media": [
        {
          "type": "photo",
          "previewUrl": "https://pbs.twimg.com/media/HLW2ADoaYAAtgTc.jpg",
          "url": "https://pbs.twimg.com/media/HLW2ADoaYAAtgTc.jpg"
        }
      ]
    },
    {
      "type": "tweet",
      "url": "https://x.com/TrollFootball/status/2068766925266854289",
      "text": "Spain\n\nWith Yamal                                Without Yamal https://t.co/avWeHeANYp",
      "author": "TrollFootball",
      "tweetId": "2068766925266854289",
      "likes": 16362,
      "retweets": 773,
      "engagement": 17977,
      "postedAt": "2026-06-21T18:44:05.000Z",
      "avatarUrl": "https://pbs.twimg.com/profile_images/2007448817789194242/VzLmM12q_normal.jpg",
      "media": [
        {
          "type": "video",
          "previewUrl": "https://pbs.twimg.com/ext_tw_video_thumb/2023067631104974848/pu/img/EEjPIOvBwOzzhIjF.jpg",
          "url": "https://video.twimg.com/ext_tw_video/2023067631104974848/pu/vid/avc1/1440x1080/ewMDDKCTq1-_I8kW.mp4"
        }
      ]
    },
    {
      "type": "tweet",
      "url": "https://x.com/memesvsfootball/status/2068763429301784767",
      "text": "Spain vs. Saudi Arabia match highlights.. https://t.co/9MEKOSC1vx",
      "author": "memesvsfootball",
      "tweetId": "2068763429301784767",
      "likes": 2396,
      "retweets": 218,
      "engagement": 2857,
      "postedAt": "2026-06-21T18:30:11.000Z",
      "avatarUrl": "https://pbs.twimg.com/profile_images/2017804319270309895/TqBzYvKY_normal.png",
      "media": [
        {
          "type": "video",
          "previewUrl": "https://pbs.twimg.com/amplify_video_thumb/2068763050413633536/img/KwiRuGN56smW4EQy.jpg",
          "url": "https://video.twimg.com/amplify_video/2068763050413633536/vid/avc1/480x720/GJ1bSYfhCMFemQLa.mp4"
        }
      ]
    }
  ],
  "belgium~iran": [
    {
      "type": "tweet",
      "url": "https://x.com/TrollFootball/status/2068820900028580208",
      "text": "🚨 VAR team that disallowed Iran's goal https://t.co/Itn7WBtLUR",
      "author": "TrollFootball",
      "tweetId": "2068820900028580208",
      "likes": 77295,
      "retweets": 6482,
      "engagement": 90685,
      "postedAt": "2026-06-21T22:18:34.000Z",
      "avatarUrl": "https://pbs.twimg.com/profile_images/2007448817789194242/VzLmM12q_normal.jpg",
      "media": [
        {
          "type": "photo",
          "previewUrl": "https://pbs.twimg.com/media/HLXrgUWbsAA6Gse.jpg",
          "url": "https://pbs.twimg.com/media/HLXrgUWbsAA6Gse.jpg"
        }
      ]
    },
    {
      "type": "tweet",
      "url": "https://x.com/TrollFootball/status/2068808526143860896",
      "text": "Donald Trump seeing Iran is unbeaten on US soil\n \nhttps://t.co/JI4zGKn7w7",
      "author": "TrollFootball",
      "tweetId": "2068808526143860896",
      "likes": 77150,
      "retweets": 4641,
      "engagement": 86675,
      "postedAt": "2026-06-21T21:29:23.000Z",
      "avatarUrl": "https://pbs.twimg.com/profile_images/2007448817789194242/VzLmM12q_normal.jpg",
      "media": [
        {
          "type": "video",
          "previewUrl": "https://pbs.twimg.com/amplify_video_thumb/2068807663417438208/img/MGPNMVcuvzvYeG-m.jpg",
          "url": "https://video.twimg.com/amplify_video/2068807663417438208/vid/avc1/720x528/Lnz51trXcM09CaOL.mp4"
        }
      ]
    },
    {
      "type": "tweet",
      "url": "https://x.com/TrollFootball/status/2068817372857938187",
      "text": "Western media be like: “Iranians took a Belgian player hostage after the game.” https://t.co/eLgCOl5gFv",
      "author": "TrollFootball",
      "tweetId": "2068817372857938187",
      "likes": 50909,
      "retweets": 3006,
      "engagement": 57073,
      "postedAt": "2026-06-21T22:04:33.000Z",
      "avatarUrl": "https://pbs.twimg.com/profile_images/2007448817789194242/VzLmM12q_normal.jpg",
      "media": [
        {
          "type": "photo",
          "previewUrl": "https://pbs.twimg.com/media/HLXqZfPaIAASQ-K.jpg",
          "url": "https://pbs.twimg.com/media/HLXqZfPaIAASQ-K.jpg"
        }
      ]
    }
  ],
  "capeverde~uruguay": [
    {
      "type": "tweet",
      "url": "https://x.com/TrollFootball/status/2068867526600413478",
      "text": "Spain and Uruguay against Cabo Verde https://t.co/xtlgUwfQG2",
      "author": "TrollFootball",
      "tweetId": "2068867526600413478",
      "likes": 6721,
      "retweets": 620,
      "engagement": 7990,
      "postedAt": "2026-06-22T01:23:50.000Z",
      "avatarUrl": "https://pbs.twimg.com/profile_images/2007448817789194242/VzLmM12q_normal.jpg",
      "media": [
        {
          "type": "video",
          "previewUrl": "https://pbs.twimg.com/amplify_video_thumb/2068852375637704704/img/M9wSg5maKjXHGTjo.jpg",
          "url": "https://video.twimg.com/amplify_video/2068852375637704704/vid/avc1/960x540/rr7iYiP6xtFWrBay.mp4"
        }
      ]
    }
  ],
  "egypt~newzealand": [
    {
      "type": "tweet",
      "url": "https://x.com/TrollFootball/status/2068891949936070988",
      "text": "Egypt against New Zealand https://t.co/AJgTdLKd0r",
      "author": "TrollFootball",
      "tweetId": "2068891949936070988",
      "likes": 57020,
      "retweets": 5341,
      "engagement": 68312,
      "postedAt": "2026-06-22T03:00:53.000Z",
      "avatarUrl": "https://pbs.twimg.com/profile_images/2007448817789194242/VzLmM12q_normal.jpg",
      "media": [
        {
          "type": "photo",
          "previewUrl": "https://pbs.twimg.com/media/HLYtLM3acAAxsx-.jpg",
          "url": "https://pbs.twimg.com/media/HLYtLM3acAAxsx-.jpg"
        }
      ]
    },
    {
      "type": "tweet",
      "url": "https://x.com/TrollFootball/status/2068894831599141175",
      "text": "New Zealand fans watching that 2nd half performance against Egypt https://t.co/qeBve9AyB3",
      "author": "TrollFootball",
      "tweetId": "2068894831599141175",
      "likes": 23237,
      "retweets": 1130,
      "engagement": 25571,
      "postedAt": "2026-06-22T03:12:20.000Z",
      "avatarUrl": "https://pbs.twimg.com/profile_images/2007448817789194242/VzLmM12q_normal.jpg",
      "media": [
        {
          "type": "photo",
          "previewUrl": "https://pbs.twimg.com/media/HLYw4ChbUAAKeMx.jpg",
          "url": "https://pbs.twimg.com/media/HLYw4ChbUAAKeMx.jpg"
        }
      ]
    },
    {
      "type": "tweet",
      "url": "https://x.com/memesvsfootball/status/2068891991010877669",
      "text": "New Zealand vs. Egypt https://t.co/up1hgbiIvv",
      "author": "memesvsfootball",
      "tweetId": "2068891991010877669",
      "likes": 8537,
      "retweets": 597,
      "engagement": 9759,
      "postedAt": "2026-06-22T03:01:03.000Z",
      "avatarUrl": "https://pbs.twimg.com/profile_images/2017804319270309895/TqBzYvKY_normal.png",
      "media": [
        {
          "type": "photo",
          "previewUrl": "https://pbs.twimg.com/media/HLYsFsXaYAAcyYa.jpg",
          "url": "https://pbs.twimg.com/media/HLYsFsXaYAAcyYa.jpg"
        }
      ]
    }
  ],
  "argentina~austria": [
    {
      "type": "tweet",
      "url": "https://x.com/TrollFootball/status/2069134700569096545",
      "text": "World Cup 2026:\n\nArgentina: 5 goals, Messi: 5 goals https://t.co/U2DldVrOAN",
      "author": "TrollFootball",
      "tweetId": "2069134700569096545",
      "likes": 62753,
      "retweets": 4413,
      "engagement": 71771,
      "postedAt": "2026-06-22T19:05:29.000Z",
      "avatarUrl": "https://pbs.twimg.com/profile_images/2007448817789194242/VzLmM12q_normal.jpg",
      "media": [
        {
          "type": "photo",
          "previewUrl": "https://pbs.twimg.com/media/HLcKk0bbcAA87VY.jpg",
          "url": "https://pbs.twimg.com/media/HLcKk0bbcAA87VY.jpg"
        }
      ]
    },
    {
      "type": "tweet",
      "url": "https://x.com/TrollFootball/status/2069133392021696697",
      "text": "Trying to hate watch 38 year old Messi \n\nhttps://t.co/M2mQjc2xsT",
      "author": "TrollFootball",
      "tweetId": "2069133392021696697",
      "likes": 48439,
      "retweets": 2068,
      "engagement": 52754,
      "postedAt": "2026-06-22T19:00:17.000Z",
      "avatarUrl": "https://pbs.twimg.com/profile_images/2007448817789194242/VzLmM12q_normal.jpg",
      "media": [
        {
          "type": "video",
          "previewUrl": "https://pbs.twimg.com/amplify_video_thumb/2020187741183758336/img/r5Qji6E0h5B1MDtN.jpg",
          "url": "https://video.twimg.com/amplify_video/2020187741183758336/vid/avc1/576x462/LTuzf2DTqu0yELGU.mp4?tag=14"
        }
      ]
    },
    {
      "type": "tweet",
      "url": "https://x.com/Contxtfootball/status/2069139621447913555",
      "text": "Messi 5 goals in 2 games at the World Cup \n\nI don’t even know what to say anymore https://t.co/QEwb3X8B9D",
      "author": "Contxtfootball",
      "tweetId": "2069139621447913555",
      "likes": 0,
      "retweets": 0,
      "engagement": 0,
      "postedAt": "2026-06-22T19:25:03.000Z",
      "avatarUrl": "https://pbs.twimg.com/profile_images/1944187419017859073/3KjUtvDF_normal.jpg",
      "media": [
        {
          "type": "photo",
          "previewUrl": "https://pbs.twimg.com/media/HLcPhBtW0AAP0Wk.jpg",
          "url": "https://pbs.twimg.com/media/HLcPhBtW0AAP0Wk.jpg"
        }
      ]
    },
    {
      "type": "tweet",
      "url": "https://x.com/memesvsfootball/status/2069133321867559145",
      "text": "Argentina vs. Jordan next.. https://t.co/evPxgjWQLg",
      "author": "memesvsfootball",
      "tweetId": "2069133321867559145",
      "likes": 42909,
      "retweets": 3105,
      "engagement": 49553,
      "postedAt": "2026-06-22T19:00:01.000Z",
      "avatarUrl": "https://pbs.twimg.com/profile_images/2017804319270309895/TqBzYvKY_normal.png",
      "media": [
        {
          "type": "video",
          "previewUrl": "https://pbs.twimg.com/amplify_video_thumb/2069131012685361152/img/g0RV1guPyjvlqdP0.jpg",
          "url": "https://video.twimg.com/amplify_video/2069131012685361152/vid/avc1/600x400/O5PTlOMc-yAIidTd.mp4"
        }
      ]
    }
  ],
  "france~iraq": [
    {
      "type": "tweet",
      "url": "https://x.com/TrollFootball/status/2069199337159377252",
      "text": "France vs Iraq https://t.co/ayDXA1plXe",
      "author": "TrollFootball",
      "tweetId": "2069199337159377252",
      "likes": 31125,
      "retweets": 1995,
      "engagement": 35268,
      "postedAt": "2026-06-22T23:22:20.000Z",
      "avatarUrl": "https://pbs.twimg.com/profile_images/2007448817789194242/VzLmM12q_normal.jpg",
      "media": [
        {
          "type": "photo",
          "previewUrl": "https://pbs.twimg.com/media/HLdFlP0asAAhJ7h.jpg",
          "url": "https://pbs.twimg.com/media/HLdFlP0asAAhJ7h.jpg"
        }
      ]
    },
    {
      "type": "tweet",
      "url": "https://x.com/TrollFootball/status/2069215413876167109",
      "text": "Mbappe against Iraq https://t.co/jILfpQjfav",
      "author": "TrollFootball",
      "tweetId": "2069215413876167109",
      "likes": 25962,
      "retweets": 1394,
      "engagement": 29289,
      "postedAt": "2026-06-23T00:26:13.000Z",
      "avatarUrl": "https://pbs.twimg.com/profile_images/2007448817789194242/VzLmM12q_normal.jpg",
      "media": [
        {
          "type": "photo",
          "previewUrl": "https://pbs.twimg.com/media/HLdUcFraQAAobyA.jpg",
          "url": "https://pbs.twimg.com/media/HLdUcFraQAAobyA.jpg"
        }
      ]
    },
    {
      "type": "tweet",
      "url": "https://x.com/TrollFootball/status/2069206152399991260",
      "text": "Americans: No, you cannot play in rain, it's dangerous for you.\n\nIraqi players in Gulf Cup:  https://t.co/J8PiQLi6kC",
      "author": "TrollFootball",
      "tweetId": "2069206152399991260",
      "likes": 9153,
      "retweets": 399,
      "engagement": 10016,
      "postedAt": "2026-06-22T23:49:25.000Z",
      "avatarUrl": "https://pbs.twimg.com/profile_images/2007448817789194242/VzLmM12q_normal.jpg",
      "media": [
        {
          "type": "video",
          "previewUrl": "https://pbs.twimg.com/amplify_video_thumb/2069183591880208384/img/NVbMeU2wR3s4M8_B.jpg",
          "url": "https://video.twimg.com/amplify_video/2069183591880208384/vid/avc1/576x576/swHPeIQYY-iGuYlP.mp4"
        }
      ]
    }
  ],
  "algeria~jordan": [
    {
      "type": "tweet",
      "url": "https://x.com/TrollFootball/status/2069287775892070558",
      "text": "Jordan vs Algeria https://t.co/wpGNaDSSTJ",
      "author": "TrollFootball",
      "tweetId": "2069287775892070558",
      "likes": 9271,
      "retweets": 474,
      "engagement": 10274,
      "postedAt": "2026-06-23T05:13:45.000Z",
      "avatarUrl": "https://pbs.twimg.com/profile_images/2007448817789194242/VzLmM12q_normal.jpg",
      "media": [
        {
          "type": "photo",
          "previewUrl": "https://pbs.twimg.com/media/HLeWNm8bYAAtxMQ.jpg",
          "url": "https://pbs.twimg.com/media/HLeWNm8bYAAtxMQ.jpg"
        }
      ]
    },
    {
      "type": "tweet",
      "url": "https://x.com/memesvsfootball/status/2069284457786609953",
      "text": "Jordan vs. Algeria match highlights.. https://t.co/HifwwLVENA",
      "author": "memesvsfootball",
      "tweetId": "2069284457786609953",
      "likes": 2511,
      "retweets": 181,
      "engagement": 2895,
      "postedAt": "2026-06-23T05:00:34.000Z",
      "avatarUrl": "https://pbs.twimg.com/profile_images/2017804319270309895/TqBzYvKY_normal.png",
      "media": [
        {
          "type": "photo",
          "previewUrl": "https://pbs.twimg.com/media/HLeSaXkboAAAd-c.jpg",
          "url": "https://pbs.twimg.com/media/HLeSaXkboAAAd-c.jpg"
        }
      ]
    }
  ],
  "portugal~uzbekistan": [
    {
      "type": "tweet",
      "url": "https://x.com/TrollFootball/status/2069496715791708612",
      "text": "Ronaldo has arrived at the World Cup https://t.co/OIu90Qy2uz",
      "author": "TrollFootball",
      "tweetId": "2069496715791708612",
      "likes": 61830,
      "retweets": 4953,
      "engagement": 72050,
      "postedAt": "2026-06-23T19:04:01.000Z",
      "avatarUrl": "https://pbs.twimg.com/profile_images/2007448817789194242/VzLmM12q_normal.jpg",
      "media": [
        {
          "type": "video",
          "previewUrl": "https://pbs.twimg.com/amplify_video_thumb/2069496544219602944/img/JgpC_fKxZR02yFve.jpg",
          "url": "https://video.twimg.com/amplify_video/2069496544219602944/vid/avc1/888x1266/ulEtpZd6XPtlbg8B.mp4"
        }
      ]
    },
    {
      "type": "tweet",
      "url": "https://x.com/Contxtfootball/status/2069500975178506620",
      "text": "Of course, Ronaldo has finally found his level.😂 https://t.co/WCF7COwyez",
      "author": "Contxtfootball",
      "tweetId": "2069500975178506620",
      "likes": 0,
      "retweets": 0,
      "engagement": 0,
      "postedAt": "2026-06-23T19:20:56.000Z",
      "avatarUrl": "https://pbs.twimg.com/profile_images/1944187419017859073/3KjUtvDF_normal.jpg",
      "media": [
        {
          "type": "photo",
          "previewUrl": "https://pbs.twimg.com/media/HLhYKQ6WgAAWIOL.jpg",
          "url": "https://pbs.twimg.com/media/HLhYKQ6WgAAWIOL.jpg"
        }
      ]
    }
  ],
  "england~ghana": [
    {
      "type": "tweet",
      "url": "https://x.com/TrollFootball/status/2069544944575119809",
      "text": "England: Can’t believe nothing worked against Ghana\n\nA group of random Ghanaians: https://t.co/ZsdY96mcxP",
      "author": "TrollFootball",
      "tweetId": "2069544944575119809",
      "likes": 30028,
      "retweets": 2901,
      "engagement": 36256,
      "postedAt": "2026-06-23T22:15:39.000Z",
      "avatarUrl": "https://pbs.twimg.com/profile_images/2007448817789194242/VzLmM12q_normal.jpg",
      "media": [
        {
          "type": "video",
          "previewUrl": "https://pbs.twimg.com/amplify_video_thumb/2069539059496849408/img/ve3qZduTBW2ix-_o.jpg",
          "url": "https://video.twimg.com/amplify_video/2069539059496849408/vid/avc1/888x920/3anWG-bUhvp4Xvsx.mp4"
        }
      ]
    },
    {
      "type": "tweet",
      "url": "https://x.com/TrollFootball/status/2069542336321946025",
      "text": "England vs Ghana https://t.co/KLvrKx9ZY9",
      "author": "TrollFootball",
      "tweetId": "2069542336321946025",
      "likes": 14804,
      "retweets": 1166,
      "engagement": 17322,
      "postedAt": "2026-06-23T22:05:17.000Z",
      "avatarUrl": "https://pbs.twimg.com/profile_images/2007448817789194242/VzLmM12q_normal.jpg",
      "media": [
        {
          "type": "video",
          "previewUrl": "https://pbs.twimg.com/amplify_video_thumb/2069542137017044992/img/Pc1SBhc4CUITAHAR.jpg",
          "url": "https://video.twimg.com/amplify_video/2069542137017044992/vid/avc1/888x956/kOHfwWLG5GaUhfns.mp4"
        }
      ]
    },
    {
      "type": "tweet",
      "url": "https://x.com/memesvsfootball/status/2069541142962864622",
      "text": "England vs. Ghana https://t.co/dFEI1PkGhb",
      "author": "memesvsfootball",
      "tweetId": "2069541142962864622",
      "likes": 6507,
      "retweets": 874,
      "engagement": 8435,
      "postedAt": "2026-06-23T22:00:33.000Z",
      "avatarUrl": "https://pbs.twimg.com/profile_images/2017804319270309895/TqBzYvKY_normal.png",
      "media": [
        {
          "type": "video",
          "previewUrl": "https://pbs.twimg.com/amplify_video_thumb/2069534707952545792/img/54iX__DyZdvEC7Z7.jpg",
          "url": "https://video.twimg.com/amplify_video/2069534707952545792/vid/avc1/720x1280/xz1lBp3mS6DxJC4m.mp4"
        }
      ]
    }
  ],
  "croatia~panama": [
    {
      "type": "tweet",
      "url": "https://x.com/TrollFootball/status/2069593613647159713",
      "text": "Panama vs Croatia https://t.co/pmtKmDmOJb",
      "author": "TrollFootball",
      "tweetId": "2069593613647159713",
      "likes": 47875,
      "retweets": 2180,
      "engagement": 52503,
      "postedAt": "2026-06-24T01:29:03.000Z",
      "avatarUrl": "https://pbs.twimg.com/profile_images/2007448817789194242/VzLmM12q_normal.jpg",
      "media": [
        {
          "type": "video",
          "previewUrl": "https://pbs.twimg.com/amplify_video_thumb/2069593395421708288/img/OroF4cpi_KmYrU3Z.jpg",
          "url": "https://video.twimg.com/amplify_video/2069593395421708288/vid/avc1/888x904/rk9HjqVxmQwL4hLV.mp4"
        }
      ]
    }
  ],
  "colombia~congodr": [
    {
      "type": "tweet",
      "url": "https://x.com/TrollFootball/status/2069634545385914412",
      "text": "Top of the group, through to knockouts\n\nColombians right now:\n\n https://t.co/VfAlsFiWQr",
      "author": "TrollFootball",
      "tweetId": "2069634545385914412",
      "likes": 17314,
      "retweets": 706,
      "engagement": 18798,
      "postedAt": "2026-06-24T04:11:42.000Z",
      "avatarUrl": "https://pbs.twimg.com/profile_images/2007448817789194242/VzLmM12q_normal.jpg",
      "media": [
        {
          "type": "video",
          "previewUrl": "https://pbs.twimg.com/amplify_video_thumb/2069633129569230848/img/8X4lBlUNutZ2E67B.jpg",
          "url": "https://video.twimg.com/amplify_video/2069633129569230848/vid/avc1/640x360/Ap05bZrhdATVcCsf.mp4"
        }
      ]
    },
    {
      "type": "tweet",
      "url": "https://x.com/TrollFootball/status/2069631897022742715",
      "text": "Colombians right now https://t.co/n1E7n1wyhH",
      "author": "TrollFootball",
      "tweetId": "2069631897022742715",
      "likes": 15627,
      "retweets": 930,
      "engagement": 17573,
      "postedAt": "2026-06-24T04:01:10.000Z",
      "avatarUrl": "https://pbs.twimg.com/profile_images/2007448817789194242/VzLmM12q_normal.jpg",
      "media": [
        {
          "type": "video",
          "previewUrl": "https://pbs.twimg.com/amplify_video_thumb/2069631751941705728/img/rKtq85DOUEGZzFQq.jpg",
          "url": "https://video.twimg.com/amplify_video/2069631751941705728/vid/avc1/888x1576/aIeGwmiH446y562H.mp4"
        }
      ]
    }
  ],
  "bosniaherzegovina~qatar": [
    {
      "type": "tweet",
      "url": "https://x.com/TrollFootball/status/2069890097298952599",
      "text": "Bosnia vs Qatar https://t.co/fGOpDRfurz",
      "author": "TrollFootball",
      "tweetId": "2069890097298952599",
      "likes": 15488,
      "retweets": 711,
      "engagement": 16975,
      "postedAt": "2026-06-24T21:07:10.000Z",
      "avatarUrl": "https://pbs.twimg.com/profile_images/2007448817789194242/VzLmM12q_normal.jpg",
      "media": [
        {
          "type": "photo",
          "previewUrl": "https://pbs.twimg.com/media/HLm5rexbMAAcaBR.jpg",
          "url": "https://pbs.twimg.com/media/HLm5rexbMAAcaBR.jpg"
        }
      ]
    }
  ],
  "haiti~morocco": [
    {
      "type": "tweet",
      "url": "https://x.com/TrollFootball/status/2069942980606370186",
      "text": "*Me watching Brazil vs Scotland*\n\nFriend: Bro, Morocco vs Haiti is crazy! 4 goals already, let’s switch channels!\n\nMe:\n\n https://t.co/trdRqTsc3x",
      "author": "TrollFootball",
      "tweetId": "2069942980606370186",
      "likes": 8838,
      "retweets": 287,
      "engagement": 9432,
      "postedAt": "2026-06-25T00:37:18.000Z",
      "avatarUrl": "https://pbs.twimg.com/profile_images/2007448817789194242/VzLmM12q_normal.jpg",
      "media": [
        {
          "type": "video",
          "previewUrl": "https://pbs.twimg.com/amplify_video_thumb/2069942355353014272/img/32sMHpF7h7RshDnA.jpg",
          "url": "https://video.twimg.com/amplify_video/2069942355353014272/vid/avc1/828x490/NbwrqICJyhDlKK2P.mp4"
        }
      ]
    }
  ],
  "brazil~scotland": [
    {
      "type": "tweet",
      "url": "https://x.com/TrollFootball/status/2069951443403186419",
      "text": "Brazilians when they top the group but then see the group table https://t.co/GWIz4V8OyW",
      "author": "TrollFootball",
      "tweetId": "2069951443403186419",
      "likes": 23706,
      "retweets": 873,
      "engagement": 25554,
      "postedAt": "2026-06-25T01:10:56.000Z",
      "avatarUrl": "https://pbs.twimg.com/profile_images/2007448817789194242/VzLmM12q_normal.jpg",
      "media": [
        {
          "type": "video",
          "previewUrl": "https://pbs.twimg.com/amplify_video_thumb/2069951172505669632/img/_7Y5K_zvA3kXkAXY.jpg",
          "url": "https://video.twimg.com/amplify_video/2069951172505669632/vid/avc1/888x1036/qiJiiEd-Y_9Lzgkg.mp4"
        }
      ]
    },
    {
      "type": "tweet",
      "url": "https://x.com/TrollFootball/status/2069942980606370186",
      "text": "*Me watching Brazil vs Scotland*\n\nFriend: Bro, Morocco vs Haiti is crazy! 4 goals already, let’s switch channels!\n\nMe:\n\n https://t.co/trdRqTsc3x",
      "author": "TrollFootball",
      "tweetId": "2069942980606370186",
      "likes": 8838,
      "retweets": 287,
      "engagement": 9432,
      "postedAt": "2026-06-25T00:37:18.000Z",
      "avatarUrl": "https://pbs.twimg.com/profile_images/2007448817789194242/VzLmM12q_normal.jpg",
      "media": [
        {
          "type": "video",
          "previewUrl": "https://pbs.twimg.com/amplify_video_thumb/2069942355353014272/img/32sMHpF7h7RshDnA.jpg",
          "url": "https://video.twimg.com/amplify_video/2069942355353014272/vid/avc1/828x490/NbwrqICJyhDlKK2P.mp4"
        }
      ]
    }
  ],
  "southafrica~southkorea": [
    {
      "type": "tweet",
      "url": "https://x.com/TrollFootball/status/2069987672484184361",
      "text": "Africans who stayed up all night hoping South Africa would lose 💀\n https://t.co/K893sZzuzU",
      "author": "TrollFootball",
      "tweetId": "2069987672484184361",
      "likes": 40698,
      "retweets": 4952,
      "engagement": 51306,
      "postedAt": "2026-06-25T03:34:54.000Z",
      "avatarUrl": "https://pbs.twimg.com/profile_images/2007448817789194242/VzLmM12q_normal.jpg",
      "media": [
        {
          "type": "video",
          "previewUrl": "https://pbs.twimg.com/amplify_video_thumb/2069987089090064384/img/_wRC9R64hwxe8xVL.jpg",
          "url": "https://video.twimg.com/amplify_video/2069987089090064384/vid/avc1/888x1466/EMH4bl6dUdLdblvw.mp4"
        }
      ]
    },
    {
      "type": "tweet",
      "url": "https://x.com/TrollFootball/status/2069981821081878657",
      "text": "South Koreans this World Cup https://t.co/s98cxILCDD",
      "author": "TrollFootball",
      "tweetId": "2069981821081878657",
      "likes": 37122,
      "retweets": 2265,
      "engagement": 41838,
      "postedAt": "2026-06-25T03:11:39.000Z",
      "avatarUrl": "https://pbs.twimg.com/profile_images/2007448817789194242/VzLmM12q_normal.jpg",
      "media": [
        {
          "type": "photo",
          "previewUrl": "https://pbs.twimg.com/media/HLoNSNXa0AEP-f2.jpg",
          "url": "https://pbs.twimg.com/media/HLoNSNXa0AEP-f2.jpg"
        }
      ]
    }
  ],
  "ecuador~germany": [
    {
      "type": "tweet",
      "url": "https://x.com/TrollFootball/status/2070277901791150574",
      "text": "Ecuador vs Germany match highlights https://t.co/NWaWQuFtzD",
      "author": "TrollFootball",
      "tweetId": "2070277901791150574",
      "likes": 15507,
      "retweets": 1273,
      "engagement": 18136,
      "postedAt": "2026-06-25T22:48:10.000Z",
      "avatarUrl": "https://pbs.twimg.com/profile_images/2007448817789194242/VzLmM12q_normal.jpg",
      "media": [
        {
          "type": "video",
          "previewUrl": "https://pbs.twimg.com/amplify_video_thumb/2070277725043249152/img/yFztEpR1LhRWDkJx.jpg",
          "url": "https://video.twimg.com/amplify_video/2070277725043249152/vid/avc1/888x756/LrQ0X-XFI9gmmtcV.mp4"
        }
      ]
    },
    {
      "type": "tweet",
      "url": "https://x.com/Contxtfootball/status/2070267698970321291",
      "text": "How is Germany lose against Ecuador https://t.co/nEjY2IQp2Y",
      "author": "Contxtfootball",
      "tweetId": "2070267698970321291",
      "likes": 0,
      "retweets": 0,
      "engagement": 0,
      "postedAt": "2026-06-25T22:07:37.000Z",
      "avatarUrl": "https://pbs.twimg.com/profile_images/1944187419017859073/3KjUtvDF_normal.jpg",
      "media": [
        {
          "type": "photo",
          "previewUrl": "https://pbs.twimg.com/media/HLsRfx3WIAAC0Xg.jpg",
          "url": "https://pbs.twimg.com/media/HLsRfx3WIAAC0Xg.jpg"
        }
      ]
    }
  ],
  "australia~paraguay": [
    {
      "type": "tweet",
      "url": "https://x.com/TrollFootball/status/2070366364938932253",
      "text": "A moment of silence for those who watched Australia vs Paraguay. Even the people of these countries. https://t.co/WfEQSfWcJy",
      "author": "TrollFootball",
      "tweetId": "2070366364938932253",
      "likes": 19448,
      "retweets": 1195,
      "engagement": 21954,
      "postedAt": "2026-06-26T04:39:41.000Z",
      "avatarUrl": "https://pbs.twimg.com/profile_images/2007448817789194242/VzLmM12q_normal.jpg",
      "media": [
        {
          "type": "photo",
          "previewUrl": "https://pbs.twimg.com/media/HLtp_k1aIAAit8k.jpg",
          "url": "https://pbs.twimg.com/media/HLtp_k1aIAAit8k.jpg"
        }
      ]
    }
  ],
  "turkiye~unitedstates": [
    {
      "type": "tweet",
      "url": "https://x.com/TrollFootball/status/2070356895760785802",
      "text": "Türkiye when absolutely nothing is on the line\n\nhttps://t.co/HG3gKirp0M",
      "author": "TrollFootball",
      "tweetId": "2070356895760785802",
      "likes": 98600,
      "retweets": 3544,
      "engagement": 105965,
      "postedAt": "2026-06-26T04:02:03.000Z",
      "avatarUrl": "https://pbs.twimg.com/profile_images/2007448817789194242/VzLmM12q_normal.jpg",
      "media": [
        {
          "type": "video",
          "previewUrl": "https://pbs.twimg.com/amplify_video_thumb/2070341509510287361/img/PSY3WLEWzHH_YlzF.jpg",
          "url": "https://video.twimg.com/amplify_video/2070341509510287361/vid/avc1/1272x720/tF0u1nSfICsGG383.mp4"
        }
      ]
    },
    {
      "type": "tweet",
      "url": "https://x.com/TrollFootball/status/2070375700016795940",
      "text": "USA vs Türkiye https://t.co/KV3UEiMUTk",
      "author": "TrollFootball",
      "tweetId": "2070375700016795940",
      "likes": 36512,
      "retweets": 1261,
      "engagement": 39147,
      "postedAt": "2026-06-26T05:16:47.000Z",
      "avatarUrl": "https://pbs.twimg.com/profile_images/2007448817789194242/VzLmM12q_normal.jpg",
      "media": [
        {
          "type": "video",
          "previewUrl": "https://pbs.twimg.com/amplify_video_thumb/2070375487097151488/img/aAN8i5jBxXGu5G6c.jpg",
          "url": "https://video.twimg.com/amplify_video/2070375487097151488/vid/avc1/360x360/tooCN-HJji2iw7aj.mp4"
        }
      ]
    }
  ],
  "france~norway": [
    {
      "type": "tweet",
      "url": "https://x.com/TrollFootball/status/2070633343260274995",
      "text": "When Mbappe speaks, you listen! https://t.co/pCtNZcZ6Qi",
      "author": "TrollFootball",
      "tweetId": "2070633343260274995",
      "likes": 67008,
      "retweets": 5029,
      "engagement": 77379,
      "postedAt": "2026-06-26T22:20:34.000Z",
      "avatarUrl": "https://pbs.twimg.com/profile_images/2007448817789194242/VzLmM12q_normal.jpg",
      "media": [
        {
          "type": "photo",
          "previewUrl": "https://pbs.twimg.com/media/HLxd_d_bMAA7jTA.jpg",
          "url": "https://pbs.twimg.com/media/HLxd_d_bMAA7jTA.jpg"
        }
      ]
    },
    {
      "type": "tweet",
      "url": "https://x.com/TrollFootball/status/2070617564452196486",
      "text": "Haaland from the bench watching France thrash Norway https://t.co/7cIkjmXuvq",
      "author": "TrollFootball",
      "tweetId": "2070617564452196486",
      "likes": 26017,
      "retweets": 2224,
      "engagement": 30684,
      "postedAt": "2026-06-26T21:17:52.000Z",
      "avatarUrl": "https://pbs.twimg.com/profile_images/2007448817789194242/VzLmM12q_normal.jpg",
      "media": [
        {
          "type": "video",
          "previewUrl": "https://pbs.twimg.com/amplify_video_thumb/2070617387054055424/img/eQrCQgTdoanddLd_.jpg",
          "url": "https://video.twimg.com/amplify_video/2070617387054055424/vid/avc1/1078x1158/wtjEntiqanYIxcNi.mp4"
        }
      ]
    }
  ],
  "france~paraguay": [
    {
      "type": "tweet",
      "url": "https://x.com/TrollFootball/status/2073557235620565246",
      "text": "Paraguay vs France match highlights",
      "author": "TrollFootball",
      "tweetId": "2073557235620565246",
      "likes": 12616,
      "retweets": 1316,
      "engagement": 15248,
      "postedAt": "2026-07-04T23:59:04.000Z",
      "avatarUrl": "https://pbs.twimg.com/profile_images/2007448817789194242/VzLmM12q_normal.jpg",
      "media": [
        {
          "type": "video",
          "previewUrl": "https://pbs.twimg.com/amplify_video_thumb/2073552105047306240/img/rUvGSdpdhLKMe6Jd.jpg",
          "url": "https://video.twimg.com/amplify_video/2073552105047306240/vid/avc1/600x400/aLPOD9WlBKd5FviP.mp4"
        }
      ]
    }
  ],
  "brazil~norway": [
    {
      "type": "tweet",
      "url": "https://x.com/TrollFootball/status/2073899801721311324",
      "text": "Norway goalkeeper Nyland against Brasil:  https://t.co/eWZ845yMcU",
      "author": "TrollFootball",
      "tweetId": "2073899801721311324",
      "likes": 9146,
      "retweets": 711,
      "engagement": 10610,
      "postedAt": "2026-07-05T22:40:18.000Z",
      "avatarUrl": "https://pbs.twimg.com/profile_images/2007448817789194242/VzLmM12q_normal.jpg",
      "media": [
        {
          "type": "video",
          "previewUrl": "https://pbs.twimg.com/amplify_video_thumb/2073893938638073856/img/4NbfjKPmk1in_0CM.jpg",
          "url": "https://video.twimg.com/amplify_video/2073893938638073856/vid/avc1/1080x720/JORgh5HXyZYTA_at.mp4"
        }
      ]
    },
    {
      "type": "tweet",
      "url": "https://x.com/memesvsfootball/status/2073902241140912176",
      "text": "Brazil vs. Norway match highlights.. https://t.co/LAzMQx4XBG",
      "author": "memesvsfootball",
      "tweetId": "2073902241140912176",
      "likes": 240,
      "retweets": 27,
      "engagement": 294,
      "postedAt": "2026-07-05T22:50:00.000Z",
      "avatarUrl": "https://pbs.twimg.com/profile_images/2017804319270309895/TqBzYvKY_normal.png",
      "media": [
        {
          "type": "video",
          "previewUrl": "https://pbs.twimg.com/amplify_video_thumb/2073901787510353920/img/R5Dz2H7xxsV3Mfq-.jpg",
          "url": "https://video.twimg.com/amplify_video/2073901787510353920/vid/avc1/720x720/At-kW9y7qtHVEbQI.mp4"
        }
      ]
    }
  ]
}